<?xml version="1.0" encoding="utf-8"?>
<clothing-items>
 <clothing>
  <id>
   864262895
  </id>
  <name>
   Converse Blouse Y-8619
  </name>
  <category>
   Blouse
  </category>
  <size>
   XXL
  </size>
  <color>
   Голубой
  </color>
  <material>
   Нейлон
  </material>
  <price>
   278430
  </price>
  <rating>
   1.94
  </rating>
  <reviews>
   772247
  </reviews>
  <new>
   +
  </new>
  <exclusive>
   yes
  </exclusive>
 </clothing>
 <clothing>
  <id>
   495784242
  </id>
  <name>
   PleinSport Sweater T-4564
  </name>
  <category>
   Sweater
  </category>
  <size>
   M
  </size>
  <color>
   Фиолетовый
  </color>
  <material>
   Шерсть
  </material>
  <price>
   568691
  </price>
  <rating>
   3.72
  </rating>
  <reviews>
   679170
  </reviews>
  <sporty>
   no
  </sporty>
 </clothing>
 <clothing>
  <id>
   412832383
  </id>
  <name>
   Asics Pants C-4178
  </name>
  <category>
   Pants
  </category>
  <size>
   L
  </size>
  <color>
   Зеленый
  </color>
  <material>
   Полиэстер
  </material>
  <price>
   245765
  </price>
  <rating>
   3.79
  </rating>
  <reviews>
   329372
  </reviews>
  <new>
   -
  </new>
  <sporty>
   yes
  </sporty>
 </clothing>
 <clothing>
  <id>
   764778564
  </id>
  <name>
   New Balance Socks U-4893
  </name>
  <category>
   Socks
  </category>
  <size>
   S
  </size>
  <color>
   Оранжевый
  </color>
  <material>
   Лен
  </material>
  <price>
   302598
  </price>
  <rating>
   4.86
  </rating>
  <reviews>
   424282
  </reviews>
  <new>
   +
  </new>
  <sporty>
   yes
  </sporty>
 </clothing>
 <clothing>
  <id>
   139414033
  </id>
  <name>
   Asics Handbags B-4446
  </name>
  <category>
   Handbags
  </category>
  <size>
   M
  </size>
  <color>
   Фиолетовый
  </color>
  <material>
   Шелк
  </material>
  <price>
   231848
  </price>
  <rating>
   1.97
  </rating>
  <reviews>
   162055
  </reviews>
  <exclusive>
   no
  </exclusive>
 </clothing>
 <clothing>
  <id>
   314406296
  </id>
  <name>
   Adidas Sweater Y-5741
  </name>
  <category>
   Sweater
  </category>
  <size>
   XXL
  </size>
  <color>
   Красный
  </color>
  <material>
   Шерсть
  </material>
  <price>
   975071
  </price>
  <rating>
   2.56
  </rating>
  <reviews>
   849456
  </reviews>
  <sporty>
   no
  </sporty>
 </clothing>
 <clothing>
  <id>
   646441375
  </id>
  <name>
   Brooks Pants R-3688
  </name>
  <category>
   Pants
  </category>
  <size>
   S
  </size>
  <color>
   Зеленый
  </color>
  <material>
   Шелк
  </material>
  <price>
   130512
  </price>
  <rating>
   2.32
  </rating>
  <reviews>
   601351
  </reviews>
  <new>
   +
  </new>
  <exclusive>
   yes
  </exclusive>
  <sporty>
   yes
  </sporty>
 </clothing>
 <clothing>
  <id>
   986060864
  </id>
  <name>
   Addidas Gloves L-4064
  </name>
  <category>
   Gloves
  </category>
  <size>
   M
  </size>
  <color>
   Фиолетовый
  </color>
  <material>
   Шелк
  </material>
  <price>
   618714
  </price>
  <rating>
   4.88
  </rating>
  <reviews>
   613913
  </reviews>
  <new>
   -
  </new>
  <exclusive>
   yes
  </exclusive>
 </clothing>
 <clothing>
  <id>
   748235955
  </id>
  <name>
   Addidas T-shirt E-9796
  </name>
  <category>
   T-shirt
  </category>
  <size>
   XXL
  </size>
  <color>
   Голубой
  </color>
  <material>
   Шерсть
  </material>
  <price>
   864737
  </price>
  <rating>
   1.27
  </rating>
  <reviews>
   439856
  </reviews>
  <new>
   -
  </new>
  <exclusive>
   yes
  </exclusive>
  <sporty>
   yes
  </sporty>
 </clothing>
 <clothing>
  <id>
   797209504
  </id>
  <name>
   Fila Pants J-4610
  </name>
  <category>
   Pants
  </category>
  <size>
   M
  </size>
  <color>
   Зеленый
  </color>
  <material>
   Лен
  </material>
  <price>
   241837
  </price>
  <rating>
   2.52
  </rating>
  <reviews>
   329083
  </reviews>
  <new>
   +
  </new>
  <exclusive>
   yes
  </exclusive>
 </clothing>
 <clothing>
  <id>
   992041145
  </id>
  <name>
   Puma Shoes W-5794
  </name>
  <category>
   Shoes
  </category>
  <size>
   XXL
  </size>
  <color>
   Оранжевый
  </color>
  <material>
   Полиэстер
  </material>
  <price>
   156018
  </price>
  <rating>
   2.53
  </rating>
  <reviews>
   365735
  </reviews>
  <new>
   +
  </new>
 </clothing>
 <clothing>
  <id>
   943352513
  </id>
  <name>
   Fila Handbags W-2864
  </name>
  <category>
   Handbags
  </category>
  <size>
   M
  </size>
  <color>
   Оранжевый
  </color>
  <material>
   Кожа
  </material>
  <price>
   954737
  </price>
  <rating>
   4.63
  </rating>
  <reviews>
   269132
  </reviews>
  <new>
   -
  </new>
  <exclusive>
   no
  </exclusive>
 </clothing>
 <clothing>
  <id>
   535522897
  </id>
  <name>
   Fila Jeans E-5218
  </name>
  <category>
   Jeans
  </category>
  <size>
   XXL
  </size>
  <color>
   Голубой
  </color>
  <material>
   Шелк
  </material>
  <price>
   747646
  </price>
  <rating>
   2.08
  </rating>
  <reviews>
   534787
  </reviews>
  <exclusive>
   no
  </exclusive>
  <sporty>
   yes
  </sporty>
 </clothing>
</clothing-items>
